<?xml version="1.0"?>
<ArrayOfParcel xmlns:xsi="http://www.w3.org/2001/XMLSchema-instance" xmlns:xsd="http://www.w3.org/2001/XMLSchema">
  <Parcel>
    <CodeParcel>100000</CodeParcel>
    <SenderId>718180330</SenderId>
    <TargetId>801874968</TargetId>
    <Weight>medium</Weight>
    <Priority>normal</Priority>
    <DroneId>1</DroneId>
    <Requested>2022-01-13T06:21:27.3589195+02:00</Requested>
    <Scheduled>2022-01-13T06:21:27.3624711+02:00</Scheduled>
    <PickedUp xsi:nil="true" />
    <Delivered xsi:nil="true" />
  </Parcel>
  <Parcel>
    <CodeParcel>100001</CodeParcel>
    <SenderId>209149063</SenderId>
    <TargetId>165854788</TargetId>
    <Weight>easy</Weight>
    <Priority>normal</Priority>
    <DroneId>2</DroneId>
    <Requested>2022-01-13T06:21:27.3630158+02:00</Requested>
    <Scheduled>2022-01-13T06:21:27.3630655+02:00</Scheduled>
    <PickedUp>2022-01-13T06:47:01.6195232+02:00</PickedUp>
    <Delivered>2022-01-13T06:47:22.9571377+02:00</Delivered>
  </Parcel>
  <Parcel>
    <CodeParcel>100002</CodeParcel>
    <SenderId>714189151</SenderId>
    <TargetId>949006871</TargetId>
    <Weight>medium</Weight>
    <Priority>normal</Priority>
    <DroneId>3</DroneId>
    <Requested>2022-01-13T06:21:27.363067+02:00</Requested>
    <Scheduled>2022-01-13T06:21:27.3630684+02:00</Scheduled>
    <PickedUp xsi:nil="true" />
    <Delivered xsi:nil="true" />
  </Parcel>
  <Parcel>
    <CodeParcel>100003</CodeParcel>
    <SenderId>214107307</SenderId>
    <TargetId>437816370</TargetId>
    <Weight>medium</Weight>
    <Priority>normal</Priority>
    <DroneId>5</DroneId>
    <Requested>2022-01-13T06:21:27.363069+02:00</Requested>
    <Scheduled>2022-01-13T06:21:27.36307+02:00</Scheduled>
    <PickedUp xsi:nil="true" />
    <Delivered xsi:nil="true" />
  </Parcel>
  <Parcel>
    <CodeParcel>100004</CodeParcel>
    <SenderId>560300530</SenderId>
    <TargetId>477296017</TargetId>
    <Weight>medium</Weight>
    <Priority>express</Priority>
    <DroneId>0</DroneId>
    <Requested>2022-01-13T06:21:27.3630706+02:00</Requested>
    <Scheduled xsi:nil="true" />
    <PickedUp xsi:nil="true" />
    <Delivered xsi:nil="true" />
  </Parcel>
  <Parcel>
    <CodeParcel>100005</CodeParcel>
    <SenderId>477296017</SenderId>
    <TargetId>560300530</TargetId>
    <Weight>heavy</Weight>
    <Priority>express</Priority>
    <DroneId>0</DroneId>
    <Requested>2022-01-13T06:21:27.3631618+02:00</Requested>
    <Scheduled xsi:nil="true" />
    <PickedUp xsi:nil="true" />
    <Delivered xsi:nil="true" />
  </Parcel>
  <Parcel>
    <CodeParcel>100006</CodeParcel>
    <SenderId>437816370</SenderId>
    <TargetId>214107307</TargetId>
    <Weight>easy</Weight>
    <Priority>emergency</Priority>
    <DroneId>4</DroneId>
    <Requested>2022-01-13T06:21:27.3631639+02:00</Requested>
    <Scheduled>2022-01-13T06:21:27.3631646+02:00</Scheduled>
    <PickedUp xsi:nil="true" />
    <Delivered xsi:nil="true" />
  </Parcel>
  <Parcel>
    <CodeParcel>100007</CodeParcel>
    <SenderId>949006871</SenderId>
    <TargetId>714189151</TargetId>
    <Weight>heavy</Weight>
    <Priority>express</Priority>
    <DroneId>0</DroneId>
    <Requested>2022-01-13T06:21:27.363165+02:00</Requested>
    <Scheduled xsi:nil="true" />
    <PickedUp xsi:nil="true" />
    <Delivered xsi:nil="true" />
  </Parcel>
  <Parcel>
    <CodeParcel>100008</CodeParcel>
    <SenderId>165854788</SenderId>
    <TargetId>209149063</TargetId>
    <Weight>heavy</Weight>
    <Priority>normal</Priority>
    <DroneId>0</DroneId>
    <Requested>2022-01-13T06:21:27.3631656+02:00</Requested>
    <Scheduled xsi:nil="true" />
    <PickedUp xsi:nil="true" />
    <Delivered xsi:nil="true" />
  </Parcel>
  <Parcel>
    <CodeParcel>100009</CodeParcel>
    <SenderId>801874968</SenderId>
    <TargetId>718180330</TargetId>
    <Weight>easy</Weight>
    <Priority>normal</Priority>
    <DroneId>0</DroneId>
    <Requested>2022-01-13T06:21:27.3631662+02:00</Requested>
    <Scheduled xsi:nil="true" />
    <PickedUp xsi:nil="true" />
    <Delivered xsi:nil="true" />
  </Parcel>
  <Parcel>
    <CodeParcel>100010</CodeParcel>
    <SenderId>315842120</SenderId>
    <TargetId>718180330</TargetId>
    <Weight>easy</Weight>
    <Priority>normal</Priority>
    <DroneId>0</DroneId>
    <Requested>2022-01-13T06:31:34.6667714+02:00</Requested>
    <Scheduled xsi:nil="true" />
    <PickedUp xsi:nil="true" />
    <Delivered xsi:nil="true" />
  </Parcel>
  <Parcel>
    <CodeParcel>100011</CodeParcel>
    <SenderId>209149063</SenderId>
    <TargetId>214107307</TargetId>
    <Weight>medium</Weight>
    <Priority>express</Priority>
    <DroneId>0</DroneId>
    <Requested>2022-01-13T06:32:28.597248+02:00</Requested>
    <Scheduled xsi:nil="true" />
    <PickedUp xsi:nil="true" />
    <Delivered xsi:nil="true" />
  </Parcel>
</ArrayOfParcel>